{
  "data": [
    {
      "title": "使用入门",
      "paragraphs": [
        {
          "context": "初次进入深度操作系统，可见干净壁纸桌面及下方dock栏，点击图标运行应用，不熟悉图标可悬停看提示，右键dock栏可设高效模式。",
          "qas": [
            {
              "question": "初次进入深度操作系统，首先看到什么？",
              "id": "5-4-1",
              "answers": [
                {
                  "text": "干净的壁纸桌面",
                  "answer_start": 8
                }
              ]
            },
            {
              "question": "如何了解dock栏上不熟悉的图标对应的应用？",
              "id": "5-4-2",
              "answers": [
                {
                  "text": "将鼠标放在上面显示应用提示",
                  "answer_start": 42
                }
              ]
            },
            {
              "question": "怎样将dock栏设置成高效模式？",
              "id": "5-4-3",
              "answers": [
                {
                  "text": "右键dock栏，进行设置",
                  "answer_start": 66
                }
              ]
            }
          ]
        },
        {
          "context": "按F1键可呼出深度操作系统的帮助手册，浏览手册能让操作事半功倍，遇问题可再次打开查找答案。",
          "qas": [
            {
              "question": "如何呼出深度操作系统的帮助手册？",
              "id": "5-4-4",
              "answers": [
                {
                  "text": "按一下键盘的F1键",
                  "answer_start": 0
                }
              ]
            },
            {
              "question": "使用前浏览帮助手册有什么好处？",
              "id": "5-4-5",
              "answers": [
                {
                  "text": "让你在接下来的操作中事半功倍",
                  "answer_start": 36
                }
              ]
            }
          ]
        },
        {
          "context": "确保网线插好或无线网卡打开后，查看dock栏是否有网口或WiFi图标，点击进入网络设置并按提示操作。网卡有问题可到深度百科搜网卡词条或深度论坛求助。",
          "qas": [
            {
              "question": "连接因特网前要做什么准备？",
              "id": "5-4-6",
              "answers": [
                {
                  "text": "确保您的网线插好或者无线网卡已经打开",
                  "answer_start": 0
                }
              ]
            },
            {
              "question": "在哪里进入网络设置？",
              "id": "5-4-7",
              "answers": [
                {
                  "text": "点击dock栏上出现的像网口或者WiFi的图标",
                  "answer_start": 38
                }
              ]
            },
            {
              "question": "遇到网卡相关问题该怎么办？",
              "id": "5-4-8",
              "answers": [
                {
                  "text": "到深度百科搜索网卡词条或者到深度论坛上求助",
                  "answer_start": 85
                }
              ]
            }
          ]
        },
        {
          "context": "除dock栏显示的图标，点击启动器图标可浏览所有已安装应用，启动器类似安卓桌面应用浏览器，可直接点击运行程序，也可将程序放到dock或桌面。",
          "qas": [
            {
              "question": "如何浏览所有已安装的应用程序？",
              "id": "5-4-9",
              "answers": [
                {
                  "text": "点击启动器图标",
                  "answer_start": 20
                }
              ]
            },
            {
              "question": "启动器像什么？",
              "id": "5-4-10",
              "answers": [
                {
                  "text": "安卓桌面的应用浏览器",
                  "answer_start": 52
                }
              ]
            },
            {
              "question": "在启动器中可以对应用程序做什么操作？",
              "id": "5-4-11",
              "answers": [
                {
                  "text": "直接点击里面的程序运行，也可以将它们放到dock或者桌面上",
                  "answer_start": 76
                }
              ]
            }
          ]
        },
        {
          "context": "在dock栏或启动器中找到深度商店图标，打开后可浏览并安装常用程序。对商店使用有疑问按F1打开其帮助手册，所有带深度前缀的应用都可用F1打开对应帮助手册。",
          "qas": [
            {
              "question": "在哪里找到深度商店？",
              "id": "5-4-12",
              "answers": [
                {
                  "text": "在dock栏或者启动器中",
                  "answer_start": 0
                }
              ]
            },
            {
              "question": "对深度商店的使用有疑问时怎么办？",
              "id": "5-4-13",
              "answers": [
                {
                  "text": "在界面上按F1，打开商店的帮助手册",
                  "answer_start": 51
                }
              ]
            },
            {
              "question": "系统中带深度前缀的应用如何打开对应的帮助手册？",
              "id": "5-4-14",
              "answers": [
                {
                  "text": "使用F1键",
                  "answer_start": 95
                }
              ]
            }
          ]
        },
        {
          "context": "深度操作系统预装了chome浏览器，可打开浏览网页，也可在商店下载其他浏览器访问因特网。",
          "qas": [
            {
              "question": "深度操作系统预装了什么浏览器？",
              "id": "5-4-15",
              "answers": [
                {
                  "text": "chome浏览器",
                  "answer_start": 13
                }
              ]
            },
            {
              "question": "除了预装浏览器，还可以怎样获得其他浏览器？",
              "id": "5-4-16",
              "answers": [
                {
                  "text": "在商店中下载",
                  "answer_start": 41
                }
              ]
            }
          ]
        },
        {
          "context": "深度操作系统淡化了盘符概念，自带的深度文件管理器可让电脑文件管理有序。",
          "qas": [
            {
              "question": "深度操作系统对盘符概念做了什么处理？",
              "id": "5-4-17",
              "answers": [
                {
                  "text": "淡化了盘符概念",
                  "answer_start": 0
                }
              ]
            },
            {
              "question": "用什么工具管理电脑中的文件？",
              "id": "5-4-18",
              "answers": [
                {
                  "text": "深度文件管理器",
                  "answer_start": 16
                }
              ]
            }
          ]
        },
        {
          "context": "从dock栏打开控制中心可检查系统更新，有新版本可更新，过程中可熟悉控制中心设置内容。",
          "qas": [
            {
              "question": "如何检查系统更新？",
              "id": "5-4-19",
              "answers": [
                {
                  "text": "从dock栏上打开控制中心，检查系统更新",
                  "answer_start": 0
                }
              ]
            },
            {
              "question": "更新系统时可以做什么？",
              "id": "5-4-20",
              "answers": [
                {
                  "text": "熟悉一下控制中心的设置内容",
                  "answer_start": 42
                }
              ]
            }
          ]
        },
        {
          "context": "在启动器中搜索深度或者deepin，可找到很多深度开发的基础常用应用，今后会经常用到。",
          "qas": [
            {
              "question": "如何找到深度自己开发的应用？",
              "id": "5-4-21",
              "answers": [
                {
                  "text": "在启动器中搜索深度或者deepin",
                  "answer_start": 0
                }
              ]
            },
            {
              "question": "深度自己开发的应用有什么特点？",
              "id": "5-4-22",
              "answers": [
                {
                  "text": "一些基础又常用的应用",
                  "answer_start": 42
                }
              ]
            }
          ]
        }
      ]
    }
  ]
}